unflatten.py
unflatten-0.1.dist-info/WHEEL
unflatten-0.1.dist-info/top_level.txt
unflatten-0.1.dist-info/DESCRIPTION.rst
unflatten-0.1.dist-info/metadata.json
unflatten-0.1.dist-info/METADATA
unflatten-0.1.dist-info/zip-safe
unflatten-0.1.dist-info/RECORD
