Metadata-Version: 2.0
Name: unflatten
Version: 0.1
Summary: Unflatten dict to dict with nested dict/arrays
Home-page: https://github.com/dairiki/unflatten
Author: Jeff Dairiki
Author-email: dairiki@dairiki.org
License: UNKNOWN
Keywords: unflatten nested-dict
Platform: UNKNOWN
Classifier: Development Status :: 5 - Production/Stable
Classifier: Intended Audience :: Developers
Classifier: License :: OSI Approved :: BSD License
Classifier: Programming Language :: Python
Classifier: Programming Language :: Python :: 2.7
Classifier: Programming Language :: Python :: 3.4
Classifier: Programming Language :: Python :: 3.5
Classifier: Programming Language :: Python :: 3.6
Classifier: Programming Language :: Python :: Implementation :: PyPy
Classifier: Topic :: Software Development :: Libraries :: Python Modules
Provides-Extra: test
Requires-Dist: pytest; extra == 'test'
